setup.cfg
setup.py
pyxcli/__init__.py
pyxcli/client.py
pyxcli/errors.py
pyxcli/examples.py
pyxcli/pool.py
pyxcli/response.py
pyxcli/transports.py
pyxcli.egg-info/PKG-INFO
pyxcli.egg-info/SOURCES.txt
pyxcli.egg-info/dependency_links.txt
pyxcli.egg-info/requires.txt
pyxcli.egg-info/top_level.txt
pyxcli/events/__init__.py
pyxcli/events/events.py
pyxcli/events/platform_info.py
pyxcli/events/tests/__init__.py
pyxcli/events/tests/test_events.py
pyxcli/events/tests/test_metadata.py
pyxcli/helpers/__init__.py
pyxcli/helpers/exceptool.py
pyxcli/helpers/xml_util.py
pyxcli/mirroring/__init__.py
pyxcli/mirroring/cg_recovery_manager.py
pyxcli/mirroring/errors.py
pyxcli/mirroring/mirrored_entities.py
pyxcli/mirroring/recovery_manager.py
pyxcli/mirroring/volume_recovery_manager.py
pyxcli/mirroring/tests/__init__.py
pyxcli/mirroring/tests/test_base_recovery_manager.py
pyxcli/mirroring/tests/test_cg_recovery_manager.py
pyxcli/mirroring/tests/test_volume_recovery_manager.py