Metadata-Version: 1.1
Name: pyxcli
Version: 1.1.6
Summary: IBM Python XCLI Client
Home-page: https://github.com/IBM/pyxcli
Author: Tzur Eliyahu, Alon Marx
Author-email: tzure@il.ibm.com
License: Apache License, Version 2.0
Keywords: IBM,XIV,Spectrum Accelerate,A9000,A9000R
Platform: UNKNOWN
Classifier: Development Status :: 5 - Production/Stable
Classifier: Intended Audience :: Developers
Classifier: Intended Audience :: System Administrators
Classifier: Environment :: Console
Classifier: License :: OSI Approved :: Apache Software License
Classifier: Programming Language :: Python
Classifier: Programming Language :: Python :: 2.6
Classifier: Programming Language :: Python :: 2.7
Classifier: Topic :: Software Development :: Libraries :: Python Modules
Requires: bunch
Provides: pyxcli
